timebandit/__init__.py
timebandit/_cli.py
timebandit/timeit.py
timebandit-0.1.1.dist-info/LICENSE
timebandit-0.1.1.dist-info/WHEEL
timebandit-0.1.1.dist-info/METADATA
timebandit-0.1.1.dist-info/RECORD
