Metadata-Version: 2.1
Name: timebandit
Version: 0.1.1
Summary: The most fabulous time measuring object in the world.
Home-page: https://skeptycal.github.io/timebandit
License: Python-2.0
Keywords: macOS,setup,profile,timeit,ci,tox,cli,poetry,pyproject,toml
Author: skeptycal
Author-email: skeptycal@gmail.com
Maintainer: skeptycal
Maintainer-email: skeptycal@gmail.com 
Requires-Python: >=3.5,<4.0
Classifier: License :: OSI Approved
Classifier: License :: OSI Approved :: MIT License
Classifier: Programming Language :: Python
Classifier: Programming Language :: Python :: 3
Classifier: Programming Language :: Python :: 3.5
Classifier: Programming Language :: Python :: 3.6
Classifier: Programming Language :: Python :: 3.7
Classifier: Programming Language :: Python :: 3.8
Classifier: Programming Language :: Python :: Implementation :: CPython
Classifier: Programming Language :: Python :: Implementation :: PyPy
Requires-Dist: loguru (>=0.5.1,<0.6.0)
Requires-Dist: wheel (>=0.35.1,<0.36.0)
Project-URL: Repository, https://github.com/skeptycal/timebandit
